{
  "version": "1.1",
  "lastUpdated": "2025-10-09",
  "metadata": {
    "description": "AR家具プランナー用家具メタデータ",
    "defaultDimensions": {
      "width": 1.0,
      "height": 1.0,
      "depth": 1.0
    },
    "defaultScaling": {
      "defaultScale": 1.0,
      "maxScale": 2.0,
      "minScale": 0.3
    },
    "supportedCategories": [
      "ソファ",
      "テーブル", 
      "椅子",
      "収納",
      "テスト"
    ]
  },
  "furniture": [
    {
      "id": "test_cube_001",
      "name": "テストキューブ",
      "category": "テスト",
      "modelFileName": "test_cube.usdz",
      "thumbnailFileName": "test_cube_thumb.jpg",
      "realWorldSize": {
        "width": 0.5,
        "height": 0.5,
        "depth": 0.5
      },
      "defaultScale": 1.0,
      "maxScale": 2.0,
      "minScale": 0.5,
      "metadata": {
        "description": "基本的な立方体モデル（テスト用）",
        "tags": ["テスト", "基本形状", "立方体"],
        "materialType": "プラスチック",
        "weight": 1.0,
        "scalingStrategy": "uniform",
        "accuracyLevel": "high"
      }
    },
    {
      "id": "test_sphere_001",
      "name": "テストスフィア",
      "category": "テスト",
      "modelFileName": "test_sphere.usdz",
      "thumbnailFileName": "test_sphere_thumb.jpg",
      "realWorldSize": {
        "width": 0.6,
        "height": 0.6,
        "depth": 0.6
      },
      "defaultScale": 1.0,
      "maxScale": 2.0,
      "minScale": 0.5,
      "metadata": {
        "description": "基本的な球体モデル（テスト用）",
        "tags": ["テスト", "基本形状", "球体"],
        "materialType": "プラスチック",
        "weight": 0.8,
        "scalingStrategy": "uniform",
        "accuracyLevel": "high"
      }
    },
    {
      "id": "test_table_001",
      "name": "テストテーブル",
      "category": "テスト",
      "modelFileName": "test_table.usdz",
      "thumbnailFileName": "test_table_thumb.jpg",
      "realWorldSize": {
        "width": 1.2,
        "height": 0.75,
        "depth": 0.8
      },
      "defaultScale": 1.0,
      "maxScale": 1.5,
      "minScale": 0.7,
      "metadata": {
        "description": "シンプルなテーブルモデル（テスト用）",
        "tags": ["テスト", "テーブル", "家具"],
        "materialType": "木材",
        "weight": 15.0,
        "scalingStrategy": "uniform",
        "accuracyLevel": "medium"
      }
    },
    {
      "id": "test_chair_001",
      "name": "テストチェア",
      "category": "テスト",
      "modelFileName": "test_chair.usdz",
      "thumbnailFileName": "test_chair_thumb.jpg",
      "realWorldSize": {
        "width": 0.5,
        "height": 0.9,
        "depth": 0.5
      },
      "defaultScale": 1.0,
      "maxScale": 1.3,
      "minScale": 0.8,
      "metadata": {
        "description": "シンプルな椅子モデル（テスト用）",
        "tags": ["テスト", "椅子", "家具"],
        "materialType": "木材",
        "weight": 8.0,
        "scalingStrategy": "uniform",
        "accuracyLevel": "medium"
      }
    },
    {
      "id": "sofa_3seat_001",
      "name": "3人掛けソファ",
      "category": "ソファ",
      "modelFileName": "sofa_3seat.usdz",
      "thumbnailFileName": "sofa_3seat_thumb.jpg",
      "realWorldSize": {
        "width": 2.0,
        "height": 0.8,
        "depth": 0.9
      },
      "defaultScale": 1.0,
      "maxScale": 1.5,
      "minScale": 0.5,
      "metadata": {
        "description": "快適な3人掛けソファ",
        "tags": ["ソファ", "リビング", "3人掛け"],
        "materialType": "ファブリック",
        "weight": 45.0,
        "scalingStrategy": "uniform",
        "accuracyLevel": "high"
      }
    },
    {
      "id": "table_dining_001",
      "name": "ダイニングテーブル",
      "category": "テーブル",
      "modelFileName": "table_dining.usdz",
      "thumbnailFileName": "table_dining_thumb.jpg",
      "realWorldSize": {
        "width": 1.6,
        "height": 0.75,
        "depth": 0.9
      },
      "defaultScale": 1.0,
      "maxScale": 1.5,
      "minScale": 0.7,
      "metadata": {
        "description": "4人用ダイニングテーブル",
        "tags": ["テーブル", "ダイニング", "4人用"],
        "materialType": "木材",
        "weight": 25.0,
        "scalingStrategy": "uniform",
        "accuracyLevel": "high"
      }
    },
    {
      "id": "chair_office_001",
      "name": "オフィスチェア",
      "category": "椅子",
      "modelFileName": "chair_office.usdz",
      "thumbnailFileName": "chair_office_thumb.jpg",
      "realWorldSize": {
        "width": 0.6,
        "height": 1.2,
        "depth": 0.6
      },
      "defaultScale": 1.0,
      "maxScale": 1.3,
      "minScale": 0.8,
      "metadata": {
        "description": "エルゴノミクスオフィスチェア",
        "tags": ["椅子", "オフィス", "エルゴノミクス"],
        "materialType": "メッシュ",
        "weight": 12.0,
        "scalingStrategy": "uniform",
        "accuracyLevel": "high"
      }
    }
  ]
}